[{
    "name": "China-Guizhou",
    "address": "https://cn-gz-tcping.torch.njs.app",
    "info": "Indexyz"
}, {
    "name": "China-Shanghai",
    "address": "https://cn-sh-tcping.torch.njs.app",
    "info": "ItsLucas"
}, {
    "name": "USA-LOS",
    "address": "https://usa-los-tcping.torch.njs.app",
    "info": "Indexyz"
}, {
    "name": "China-Quanzhou",
    "address": "https://cn-qz-tcping.torch.njs.app",
    "info": "Indexyz"
}, {
    "name": "China-Guangzhou",
    "address": "https://torch-indexyz.doge.me",
    "info": "DogeSpeed https://doge.me"
}, {
    "name": "China-Qingdao",
    "address": "https://torch-ali-indexyz.doge.me",
    "info": "DogeSpeed https://doge.me"
}, {
    "name": "USA-Central",
    "address": "https://us-central1-proud-reach-201202.cloudfunctions.net/Torch",
    "info": "Indexyz, Run In Google Cloud Functions"
}, {
    "name": "China-Shanghai-Aliyun",
    "address": "https://cn-sh-01.torch.flexible.njs.app",
    "info": "WallLink https://walllink.net"
}]
